album_colours/__init__.py
album_colours/image_utils.py
album_colours/palette_generator.py
album_colours-0.1.0.dist-info/LICENSE
album_colours-0.1.0.dist-info/METADATA
album_colours-0.1.0.dist-info/WHEEL
album_colours-0.1.0.dist-info/top_level.txt
album_colours-0.1.0.dist-info/RECORD
